gpycraft/__init__.py
gpycraft/app_config.py
gpycraft/fileIO/__init__.py
gpycraft/fileIO/dotstacks.py
gpycraft/fileIO/filecraft.py
gpycraft/fileIO/radix.py
gpycraft/fireStore/__init__.py
gpycraft/fireStore/firestoreupload.py
gpycraft/googleSheet/__init__.py
gpycraft/googleSheet/gsheetsdb.py
gpycraft-1.0.3.dist-info/licenses/LICENSE
gpycraft-1.0.3.dist-info/METADATA
gpycraft-1.0.3.dist-info/WHEEL
gpycraft-1.0.3.dist-info/entry_points.txt
gpycraft-1.0.3.dist-info/top_level.txt
gpycraft-1.0.3.dist-info/RECORD
