Metadata-Version: 2.4
Name: gpycraft
Version: 1.0.3
Summary: A Python package for manipulating google sheets directly on any coding platform and perform CRUD process easily. Sheets can be stored and retrieved in firebase storage
License-File: LICENSE
Requires-Dist: firebase-admin
Requires-Dist: gspread
Requires-Dist: oauth2client
Requires-Dist: pandas
Requires-Dist: PyYAML
Requires-Dist: tqdm
Requires-Dist: xlsxwriter
Requires-Dist: openpyxl
Dynamic: description
Dynamic: description-content-type
Dynamic: license-file
Dynamic: requires-dist
Dynamic: summary
